CounterFit/__init__.py
CounterFit/actuators.py
CounterFit/binary_sensors.py
CounterFit/counterfit.py
CounterFit/i2c_sensors.py
CounterFit/sensors.py
CounterFit/serial_sensors.py
CounterFit/static/socket.io.min.js
CounterFit/static/socket.io.min.js.map
CounterFit/static/style.css
CounterFit/static/images/CounterFitLogo.png
CounterFit/static/images/favicon.png
CounterFit/templates/binary_sensor_create_settings.html
CounterFit/templates/boolean_sensor.html
CounterFit/templates/camera_sensor.html
CounterFit/templates/float_sensor.html
CounterFit/templates/gps_sensor.html
CounterFit/templates/home.html
CounterFit/templates/i2c_float_sensor.html
CounterFit/templates/i2c_integer_sensor.html
CounterFit/templates/i2c_sensor_create_settings.html
CounterFit/templates/integer_sensor.html
CounterFit/templates/led_actuator.html
CounterFit/templates/pin_sensor_create_settings.html
CounterFit/templates/relay_actuator.html
CounterFit/templates/serial_sensor_create_settings.html
tests/__init__.py
tests/test_serial_sensors.py
CounterFit-0.1.4.dev8.dist-info/LICENSE
CounterFit-0.1.4.dev8.dist-info/METADATA
CounterFit-0.1.4.dev8.dist-info/WHEEL
CounterFit-0.1.4.dev8.dist-info/entry_points.txt
CounterFit-0.1.4.dev8.dist-info/top_level.txt
CounterFit-0.1.4.dev8.dist-info/RECORD
