Metadata-Version: 2.1
Name: CounterFit
Version: 0.1.4.dev8
Summary: A virtual IoT hardware simulator.
Home-page: https://github.com/CounterFit-IoT/CounterFit
Author: Jim Bennett
Maintainer: Jim Bennett
License: MIT
Project-URL: Documentation, https://github.com/CounterFit-IoT/CounterFit
Project-URL: Source Code, https://github.com/CounterFit-IoT/CounterFit
Project-URL: Issue Tracker, https://github.com/CounterFit-IoT/CounterFit/issues
Project-URL: Twitter, https://twitter.com/JimBobBennett
Classifier: Development Status :: 2 - Pre-Alpha
Classifier: Intended Audience :: Developers
Classifier: Topic :: System :: Hardware
Classifier: License :: OSI Approved :: MIT License
Classifier: Operating System :: OS Independent
Classifier: Programming Language :: Python
Requires-Python: >=3.8
License-File: LICENSE
Requires-Dist: Flask (==2.1.2)
Requires-Dist: Flask-SocketIO (==5.2.0)
Requires-Dist: eventlet (==0.33.1)
